LICENSE
MANIFEST.in
README.md
setup.cfg
setup.py
Flask_WebSub.egg-info/PKG-INFO
Flask_WebSub.egg-info/SOURCES.txt
Flask_WebSub.egg-info/dependency_links.txt
Flask_WebSub.egg-info/not-zip-safe
Flask_WebSub.egg-info/requires.txt
Flask_WebSub.egg-info/top_level.txt
flask_websub/__init__.py
flask_websub/errors.py
flask_websub/publisher.py
flask_websub/utils.py
flask_websub/hub/__init__.py
flask_websub/hub/blueprint.py
flask_websub/hub/storage.py
flask_websub/hub/tasks.py
flask_websub/subscriber/__init__.py
flask_websub/subscriber/blueprint.py
flask_websub/subscriber/discovery.py
flask_websub/subscriber/events.py
flask_websub/subscriber/storage.py
tests/__init__.py
tests/test_integration.py
tests/test_publisher.py
tests/test_subscriber_discovery.py
tests/utils.py