Metadata-Version: 2.1
Name: Flask-WebSub
Version: 0.3.1
Summary: A WebSub hub, publisher and subscriber using Flask
Home-page: https://github.com/marten-de-vries/Flask-WebSub
Author: Marten de Vries
Author-email: m@rtendevri.es
License: ISC
Platform: any
Classifier: Environment :: Web Environment
Classifier: Intended Audience :: Developers
Classifier: License :: OSI Approved :: ISC License (ISCL)
Classifier: Operating System :: OS Independent
Classifier: Programming Language :: Python
Classifier: Programming Language :: Python :: 3
Classifier: Topic :: Internet :: WWW/HTTP :: Dynamic Content
Classifier: Topic :: Software Development :: Libraries :: Python Modules
Provides-Extra: celery
Provides-Extra: dev
Provides-Extra: redis
